data/gen_csv.py
data/gen_json.py
docs/conf.py
qtypy/__init__.py
qtypy/analyze.py
qtypy/column.py
qtypy/dataflow.py
qtypy/dataset.py
qtypy/query.py
qtypy/selection.py
qtypy/cpp/__init__.py
qtypy/cpp/binding.py
qtypy/cpp/utils.py
queryosity-0.9.2.dist-info/licenses/LICENSE
queryosity-0.9.2.dist-info/METADATA
queryosity-0.9.2.dist-info/WHEEL
queryosity-0.9.2.dist-info/entry_points.txt
queryosity-0.9.2.dist-info/top_level.txt
queryosity-0.9.2.dist-info/RECORD
