Metadata-Version: 2.4
Name: queryosity
Version: 0.9.2
Summary: Python frontend for ROOT data analyses written in queryosity
Author-email: Tae Hyoun Park <taehyounpark@icloud.com>
Project-URL: Homepage, https://queryosity.readthedocs.io/en/latest/
Project-URL: Issues, https://github.com/taehyounpark/queryosity/issues
Classifier: Programming Language :: Python :: 3
Classifier: Operating System :: OS Independent
Requires-Python: >=3.9
License-File: LICENSE
Requires-Dist: numpy
Requires-Dist: tree-sitter
Requires-Dist: tree-sitter-cpp
Requires-Dist: rich
Dynamic: license-file
